tiny_mistralai/__init__.py
tiny_mistralai/embedder.py
tiny_mistralai/llm.py
tiny_mistralai/register.py
tiny_mistralai/types.py
tiny_mistralai/utils.py
tinygent_mistralai-0.1.1007.dist-info/METADATA
tinygent_mistralai-0.1.1007.dist-info/WHEEL
tinygent_mistralai-0.1.1007.dist-info/entry_points.txt
tinygent_mistralai-0.1.1007.dist-info/RECORD
