Metadata-Version: 2.4
Name: tinygent-mistralai
Version: 0.1.1007
Requires-Dist: mistral-common>=1.8.5
Requires-Dist: mistralai>=1.9.11
Requires-Dist: tinygent
Requires-Dist: transformers>=4.57.6
